merit/__init__.py
merit/config.py
merit/assertions/__init__.py
merit/assertions/base.py
merit/assertions/transformers.py
merit/cli/__init__.py
merit/context/__init__.py
merit/context/context.py
merit/metrics_/__init__.py
merit/metrics_/base.py
merit/predicates/__init__.py
merit/predicates/ai_predicates.py
merit/predicates/base.py
merit/predicates/client.py
merit/reports/__init__.py
merit/reports/base.py
merit/reports/console.py
merit/resources/__init__.py
merit/resources/resolver.py
merit/testing/__init__.py
merit/testing/case.py
merit/testing/environment.py
merit/testing/runner.py
merit/testing/sut.py
merit/testing/decorators/__init__.py
merit/testing/decorators/parametrize.py
merit/testing/decorators/repeat.py
merit/testing/decorators/tags.py
merit/testing/discovery/__init__.py
merit/testing/discovery/collector.py
merit/testing/discovery/loader.py
merit/testing/execution/__init__.py
merit/testing/execution/factory.py
merit/testing/execution/interfaces.py
merit/testing/execution/invoker.py
merit/testing/execution/parametrized.py
merit/testing/execution/repeated.py
merit/testing/execution/result_builder.py
merit/testing/execution/single.py
merit/testing/execution/tracer.py
merit/testing/models/__init__.py
merit/testing/models/definition.py
merit/testing/models/modifiers.py
merit/testing/models/result.py
merit/testing/models/run.py
merit/tracing/__init__.py
merit/tracing/context.py
merit/tracing/exporters.py
merit/tracing/lifecycle.py
appmerit-0.1.1.dist-info/METADATA
appmerit-0.1.1.dist-info/WHEEL
appmerit-0.1.1.dist-info/entry_points.txt
appmerit-0.1.1.dist-info/licenses/LICENSE
appmerit-0.1.1.dist-info/RECORD
