Metadata-Version: 2.4
Name: appmerit
Version: 0.1.1
Summary: AI Testing Framework
Author-email: Daniel Rousso <daniel@appmerit.com>, Mark Reith <mark@appmerit.com>, Nikita Shirobokov <nick@appmerit.com>
License-Expression: MIT
License-File: LICENSE
Classifier: Programming Language :: Python :: 3
Classifier: Programming Language :: Python :: 3.12
Classifier: Programming Language :: Python :: 3.13
Classifier: Programming Language :: Python :: 3.14
Requires-Python: >=3.12
Requires-Dist: anthropic[vertex]>=0.72.0
Requires-Dist: httpx>=0.28.1
Requires-Dist: openai>=2.6.1
Requires-Dist: opentelemetry-instrumentation-anthropic>=0.49.0
Requires-Dist: opentelemetry-instrumentation-openai>=0.49.0
Requires-Dist: opentelemetry-sdk>=1.29.0
Requires-Dist: pydantic-settings>=2.11.0
Requires-Dist: pydantic>=2.12.3
Requires-Dist: python-dotenv>=1.2.1
Requires-Dist: rich>=14.2.0
